setup.py
sufi_dists/__init__.py
sufi_dists/pythoncode.py
sufi_dists.egg-info/PKG-INFO
sufi_dists.egg-info/SOURCES.txt
sufi_dists.egg-info/dependency_links.txt
sufi_dists.egg-info/not-zip-safe
sufi_dists.egg-info/top_level.txt