Metadata-Version: 1.0
Name: sufi-dists
Version: 1.1
Summary: Testing usage of packaging
Home-page: UNKNOWN
Author: Sufian Kaki Aslam
Author-email: sufiankaki@gmail.com
License: UNKNOWN
Platform: UNKNOWN
